[
  {
    "id": "ph1",
    "title": "Kedarnath light",
    "src": "/images/photos/mruvbram-1000011547.jpg",
    "collection": "Himalaya",
    "mode": "landscape",
    "favorite": true,
    "location": "Kedarnath, Uttarakhand",
    "exif": {
      "camera": "Trail camera — replace with your EXIF"
    }
  },
  {
    "id": "ph2",
    "title": "Kalavantin steps",
    "src": "/images/adventure/kalavantin.svg",
    "collection": "Sahyadri",
    "mode": "portrait",
    "favorite": true,
    "location": "Raigad, Maharashtra"
  },
  {
    "id": "ph3",
    "title": "Rajgad ridge",
    "src": "/images/adventure/rajgad.svg",
    "collection": "Sahyadri",
    "mode": "landscape",
    "location": "Pune district"
  },
  {
    "id": "ph4",
    "title": "Garbett monsoon",
    "src": "/images/photos/mruv7hns-1000233112.jpg",
    "collection": "Sahyadri",
    "mode": "landscape",
    "location": "Matheran hills"
  },
  {
    "id": "ph5",
    "title": "Gorakhgad pin",
    "src": "/images/photos/mruv84ar-1000210321.jpg",
    "collection": "Sahyadri",
    "mode": "portrait",
    "location": "Near Murbad"
  },
  {
    "id": "ph6",
    "title": "Sagargad air",
    "src": "/images/photos/mruv8voq-1000121696.jpg",
    "collection": "Konkan",
    "mode": "landscape",
    "location": "Alibag region"
  }
]
